harmony_cli/__init__.py
harmony_cli/main.py
harmony_cli-1.4.0.dist-info/licenses/LICENSE
harmony_cli-1.4.0.dist-info/METADATA
harmony_cli-1.4.0.dist-info/WHEEL
harmony_cli-1.4.0.dist-info/entry_points.txt
harmony_cli-1.4.0.dist-info/top_level.txt
harmony_cli-1.4.0.dist-info/RECORD
