Metadata-Version: 2.4
Name: harmony-cli
Version: 1.4.0
Summary: Beautiful CLI for Harmony AI - Advanced AI Assistant by Mergen AI
Home-page: https://github.com/mergen-ai/harmony-cli
Author: Mergen AI
Author-email: Mergen AI <info@mergen.az>
Maintainer-email: Mergen AI <info@mergen.az>
License: MIT
Project-URL: Homepage, https://hal-x.ai
Project-URL: Documentation, https://docs.mergen.az/harmony-cli
Project-URL: Repository, https://github.com/mergen-ai/harmony-cli
Project-URL: Bug Reports, https://github.com/mergen-ai/harmony-cli/issues
Keywords: ai,cli,harmony,mergen,assistant,chat,artificial-intelligence
Classifier: Development Status :: 5 - Production/Stable
Classifier: Intended Audience :: Developers
Classifier: Topic :: Software Development :: Libraries :: Python Modules
Classifier: Topic :: Scientific/Engineering :: Artificial Intelligence
Classifier: License :: OSI Approved :: MIT License
Classifier: Programming Language :: Python :: 3
Classifier: Programming Language :: Python :: 3.8
Classifier: Programming Language :: Python :: 3.9
Classifier: Programming Language :: Python :: 3.10
Classifier: Programming Language :: Python :: 3.11
Classifier: Programming Language :: Python :: 3.12
Classifier: Operating System :: OS Independent
Requires-Python: >=3.8
License-File: LICENSE
Requires-Dist: rich>=12.0.0
Requires-Dist: httpx>=0.24.0
Requires-Dist: colorama>=0.4.4
Dynamic: author
Dynamic: home-page
Dynamic: license-file
Dynamic: requires-python
